{
	"name": "dl_csv_dataset",
	"properties": {
		"linkedServiceName": {
			"referenceName": "AzureDataLakeStorage",
			"type": "LinkedServiceReference"
		},
		"parameters": {
			"filename": {
				"type": "String",
				"defaultValue": "Products.csv"
			}
		},
		"annotations": [],
		"type": "DelimitedText",
		"typeProperties": {
			"location": {
				"type": "AzureBlobFSLocation",
				"fileName": {
					"value": "@dataset().filename",
					"type": "Expression"
				},
				"folderPath": "raw",
				"fileSystem": "synapse"
			},
			"columnDelimiter": ",",
			"rowDelimiter": "\n",
			"escapeChar": "\"",
			"firstRowAsHeader": true,
			"quoteChar": "\""
		},
		"schema": []
	},
	"type": "Microsoft.Synapse/workspaces/datasets"
}